<?xml version='1.0' encoding='ISO-8859-1' ?>
<toc version="1.0"> 
<tocitem>XEvent-B User Manual
    <tocitem target="sec:overview">Event-B XText Front-end Overview
        
    </tocitem><tocitem target="sec:getting-started">Getting Started
        <tocitem target="sec:installation">Installation
            
        </tocitem><tocitem target="sec:basic-tutorial">Basic Tutorial
            
        </tocitem>
    </tocitem><tocitem target="sec:concepts">Concepts
        <tocitem target="sec:xtext-projects">XText Projects
            
        </tocitem><tocitem target="sec:xevent-b-builders">XEvent-B Builders
            
        </tocitem><tocitem target="sec:content-assist">Content Assist
            
        </tocitem>
    </tocitem><tocitem target="sec:tasks">Tasks
        <tocitem target="sec:creating-xevent-b">Creating XEvent-B Files
            
        </tocitem><tocitem target="sec:typesetting-event-b">Typesetting Event-B Mathematical Symbols
            
        </tocitem>
    </tocitem><tocitem target="sec:reference">Reference
        <tocitem target="sec:common-syntax">Common Syntax
            
        </tocitem><tocitem target="sec:xcontext-syntax">XContext Syntax
            
        </tocitem><tocitem target="sec:xmachine-syntax">XMachine syntax
            
        </tocitem><tocitem target="sec:preferences">Preferences
            
        </tocitem><tocitem target="sec:xevent-b-editors">XEvent-B Editors
            
        </tocitem>
    </tocitem><tocitem target="sec:legal">Legal
        <tocitem target="sec:user-agreement">RODIN Software User Agreement
            
        </tocitem>
    </tocitem>
</tocitem>
</toc>